[
  {
    "id": 0,
    "title": "Staplerfahrer/in (m/w/d) 100%",
    "location": "Svizzera",
    "sector": "Generale",
    "company": "Adecco",
    "link": "https://jobroom.jobcourier.ch/job/view-job.php?id=6690653-staplerfahrer-in-m-w-d-100-luterbach-solothurn&language=en"
  },
  {
    "id": 1,
    "title": "Manager Contentieux",
    "location": "Svizzera",
    "sector": "Generale",
    "company": "Adecco",
    "link": "https://jobroom.jobcourier.ch/job/view-job.php?id=6690662-manager-contentieux-lausanne-vaud&language=en"
  },
  {
    "id": 2,
    "title": "Menuisier avec CFC",
    "location": "Svizzera",
    "sector": "Generale",
    "company": "Adecco",
    "link": "https://jobroom.jobcourier.ch/job/view-job.php?id=6690657-menuisier-avec-cfc-lausanne-vaud&language=en"
  },
  {
    "id": 3,
    "title": "Küchenleitung (m/w/d) 100%",
    "location": "Svizzera",
    "sector": "Generale",
    "company": "Adecco",
    "link": "https://jobroom.jobcourier.ch/job/view-job.php?id=6690654-kuchenleitung-m-w-d-100-gais-ai&language=en"
  },
  {
    "id": 4,
    "title": "Kunden- Servicetechniker/in (m/w/d)",
    "location": "Svizzera",
    "sector": "Generale",
    "company": "Adecco",
    "link": "https://jobroom.jobcourier.ch/job/view-job.php?id=6690659-kunden-servicetechniker-in-m-w-d-zurich-zh&language=en"
  },
  {
    "id": 5,
    "title": "Directeur des travaux 100% CDI (H/F/D)",
    "location": "Svizzera",
    "sector": "Generale",
    "company": "Adecco",
    "link": "https://jobroom.jobcourier.ch/job/view-job.php?id=6690658-directeur-des-travaux-100-cdi-h-f-d-monthey-valais&language=en"
  },
  {
    "id": 6,
    "title": "Assistance commerciale",
    "location": "Svizzera",
    "sector": "Generale",
    "company": "Adecco",
    "link": "https://jobroom.jobcourier.ch/job/view-job.php?id=6690656-assistance-commerciale-lausanne-vaud&language=en"
  },
  {
    "id": 7,
    "title": "Anlageführer Produktionsküche",
    "location": "Svizzera",
    "sector": "Generale",
    "company": "Adecco",
    "link": "https://jobroom.jobcourier.ch/job/view-job.php?id=6690666-anlagefuhrer-produktionskuche-dietikon-zh&language=en"
  },
  {
    "id": 8,
    "title": "Spécialiste solutions IT",
    "location": "Svizzera",
    "sector": "Generale",
    "company": "Adecco",
    "link": "https://jobroom.jobcourier.ch/job/view-job.php?id=6690664-specialiste-solutions-it-lausanne-vaud&language=en"
  },
  {
    "id": 9,
    "title": "Vertriebsmitarbeiter Aussendienst Automobilbranche 100% (m/w/d)",
    "location": "Svizzera",
    "sector": "Generale",
    "company": "Adecco",
    "link": "https://jobroom.jobcourier.ch/job/view-job.php?id=6690652-vertriebsmitarbeiter-aussendienst-automobilbranche-100-m-w-d-schlieren-zh&language=en"
  },
  {
    "id": 10,
    "title": "Koch EFZ (a)",
    "location": "Svizzera",
    "sector": "Generale",
    "company": "Adecco",
    "link": "https://jobroom.jobcourier.ch/job/view-job.php?id=6690663-koch-efz-a-tschugg-be&language=en"
  },
  {
    "id": 11,
    "title": "Servicemonteur Elektro, Eigenständiger Elektroinstallateur, Vergoldeter Elektroinstallateur",
    "location": "Svizzera",
    "sector": "Generale",
    "company": "Adecco",
    "link": "https://jobroom.jobcourier.ch/job/view-job.php?id=6690660-servicemonteur-elektro-eigenst%C3%A4ndiger-elektroinstallateur-vergoldeter-elektroinstallateur-bern-be&language=en"
  }
]